viberetry/__init__.py
viberetry/viberetry.py
viberetry/config/config.py
viberetry/models/models.py
viberetry/utils/logger.py
viberetry-1.0.0.dist-info/METADATA
viberetry-1.0.0.dist-info/WHEEL
viberetry-1.0.0.dist-info/licenses/LICENSE
viberetry-1.0.0.dist-info/RECORD
