Metadata-Version: 2.4
Name: viberetry
Version: 1.0.0
Summary: When at first you don’t succeed, vibe, vibe again.
Project-URL: Homepage, https://github.com/vibe-engineers/viberetry
Project-URL: Issues, https://github.com/vibe-engineers/viberetry/issues
Author-email: vibe-engineers <vibe.engineers.team@gmail.com>, tjtanjin <cjtanjin@gmail.com>, konglyyy <kongleyi99@gmail.com>
License-File: LICENSE
Classifier: License :: OSI Approved :: MIT License
Classifier: Operating System :: OS Independent
Classifier: Programming Language :: Python :: 3
Requires-Python: >=3.0
Requires-Dist: vibetools<2.0.0,>=1.0.0
